TABICON/IOBinFile.py
TABICON/ManejoArchivos.py
TABICON/ManejoER.py
TABICON/MyListArgs.py
TABICON/MySintaxis.py
TABICON/__init__.py
TABICON-1.2.11.dist-info/LICENSE.txt
TABICON-1.2.11.dist-info/METADATA
TABICON-1.2.11.dist-info/WHEEL
TABICON-1.2.11.dist-info/top_level.txt
TABICON-1.2.11.dist-info/RECORD
