Metadata-Version: 2.1
Name: TABICON
Version: 1.2.11
Summary: Clases para el PLN y desarrollo de componentes
Home-page: https://gitlab.com/ugarciacalderon/Servicio_Social.git
Author: Ulises Garcia Calderón
Author-email: ugarciacalderon@gmail.com
Maintainer: Jonathan Rojas Simón
Maintainer-email: jrojass@uaemex.mx
License: GPL
License-File: LICENSE.txt
